reth_db_py-0.1.4.dist-info/METADATA
reth_db_py-0.1.4.dist-info/WHEEL
reth_db_py-0.1.4.dist-info/license_files/LICENSE
reth_db_py/__init__.py
reth_db_py/__init__.pyi
reth_db_py/py.typed
reth_db_py/reth_db_py.cpython-38-darwin.so
reth_db_py-0.1.4.dist-info/RECORD
