Metadata-Version: 2.1
Name: reth-db-py
Version: 0.1.4
Classifier: Programming Language :: Rust
Classifier: Programming Language :: Python :: Implementation :: CPython
Classifier: Programming Language :: Python :: Implementation :: PyPy
License-File: LICENSE
Summary: Python wrapper around reth db. Written in Rust.
License: MIT
Requires-Python: >=3.7
